MANIFEST.in
README.md
setup.py
pnp_ccv/__init__.py
pnp_ccv/admin.py
pnp_ccv/apps.py
pnp_ccv/forms.py
pnp_ccv/mapeamento.py
pnp_ccv/menu.yaml
pnp_ccv/models.py
pnp_ccv/permissions.yaml
pnp_ccv/services.py
pnp_ccv/sincronizar_unidade.py
pnp_ccv/tasks.py
pnp_ccv/urls.py
pnp_ccv/views.py
pnp_ccv/__pycache__/__init__.cpython-313.pyc
pnp_ccv/__pycache__/admin.cpython-313.pyc
pnp_ccv/__pycache__/apps.cpython-313.pyc
pnp_ccv/__pycache__/forms.cpython-313.pyc
pnp_ccv/__pycache__/mapeamento.cpython-313.pyc
pnp_ccv/__pycache__/models.cpython-313.pyc
pnp_ccv/__pycache__/services.cpython-313.pyc
pnp_ccv/__pycache__/tasks.cpython-313.pyc
pnp_ccv/__pycache__/urls.cpython-313.pyc
pnp_ccv/__pycache__/views.cpython-313.pyc
pnp_ccv/management/__init__.py
pnp_ccv/management/__pycache__/__init__.cpython-313.pyc
pnp_ccv/management/commands/__init__.py
pnp_ccv/management/commands/pnp_ccv_exportar_dados.py
pnp_ccv/management/commands/pnp_ccv_importar_dados.py
pnp_ccv/management/commands/__pycache__/__init__.cpython-313.pyc
pnp_ccv/management/commands/__pycache__/pnp_ccv_exportar_dados.cpython-313.pyc
pnp_ccv/management/commands/__pycache__/pnp_ccv_importar_dados.cpython-313.pyc
pnp_ccv/migrations/0001_initial.py
pnp_ccv/migrations/0002_remove_curso_curso_campus.py
pnp_ccv/migrations/__init__.py
pnp_ccv/migrations/__pycache__/0001_initial.cpython-313.pyc
pnp_ccv/migrations/__pycache__/0002_remove_curso_curso_campus.cpython-313.pyc
pnp_ccv/migrations/__pycache__/0002_turno.cpython-313.pyc
pnp_ccv/migrations/__pycache__/0003_curso_codigo_unidade.cpython-313.pyc
pnp_ccv/migrations/__pycache__/__init__.cpython-313.pyc
pnp_ccv/templates/alunos_ciclo.html
pnp_ccv/templates/evadidos_ciclo.html
pnp_ccv/templates/inscritos_ciclo.html
suap_pnp_ccv.egg-info/PKG-INFO
suap_pnp_ccv.egg-info/SOURCES.txt
suap_pnp_ccv.egg-info/dependency_links.txt
suap_pnp_ccv.egg-info/top_level.txt