Metadata-Version: 2.1
Name: suap_pnp_ccv
Version: 0.0.3
Summary: PNP CCV application for SUAP
Home-page: https://gitlab.ifrn.edu.br/cosinf/suap_pnp_ccv
Author: Breno Silva
Author-email: breno.silva@ifrn.edu.br
License: BSD License
Classifier: Environment :: Web Environment
Classifier: Framework :: Django
Classifier: Intended Audience :: Developers
Classifier: License :: OSI Approved :: BSD License
Classifier: Operating System :: OS Independent
Classifier: Programming Language :: Python
Classifier: Topic :: Internet :: WWW/HTTP
Classifier: Topic :: Internet :: WWW/HTTP :: Dynamic Content
